setup.py
sentry_runner/__init__.py
sentry_runner.egg-info/PKG-INFO
sentry_runner.egg-info/SOURCES.txt
sentry_runner.egg-info/dependency_links.txt
sentry_runner.egg-info/requires.txt
sentry_runner.egg-info/top_level.txt
sentry_runner/management/__init__.py
sentry_runner/management/commands/__init__.py
sentry_runner/management/commands/runner.py