Metadata-Version: 1.0
Name: sentry-runner
Version: 0.1.0
Summary: Run arbitrary script within Sentry environment
Home-page: https://github.com/eagletmt/sentry-runner
Author: Kohei Suzuki
Author-email: eagletmt@gmail.com
License: MIT
Platform: UNKNOWN
